magicfunc/__core.py
magicfunc/__init__.py
magicfunc/__log.py
magicfunc/__type.py
magicfunc/chatgpt3.py
magicfunc-1.0.1.dist-info/LICENSE
magicfunc-1.0.1.dist-info/METADATA
magicfunc-1.0.1.dist-info/WHEEL
magicfunc-1.0.1.dist-info/RECORD
