Metadata-Version: 2.1
Name: magicfunc
Version: 1.0.1
Summary: magicfunc is a Python library that uses LLM to generate function bodies for function signatures and dynamically proxies them at runtime.
License: MIT
Author: jawide
Author-email: 596929059@qq.com
Requires-Python: >=3.7.1,<4.0
Classifier: License :: OSI Approved :: MIT License
Classifier: Programming Language :: Python :: 3
Classifier: Programming Language :: Python :: 3.8
Classifier: Programming Language :: Python :: 3.9
Classifier: Programming Language :: Python :: 3.10
Classifier: Programming Language :: Python :: 3.11
Requires-Dist: openai (>=0.27.6,<0.28.0)
